a4f/__init__.py
a4f/client.py
a4f/types.py
a4f/beta/__init__.py
a4f/beta/_base_client.py
a4f/beta/_client.py
a4f/beta/_compat.py
a4f/beta/_constants.py
a4f/beta/_exceptions.py
a4f/beta/_files.py
a4f/beta/_legacy_response.py
a4f/beta/_models.py
a4f/beta/_module_client.py
a4f/beta/_qs.py
a4f/beta/_resource.py
a4f/beta/_response.py
a4f/beta/_streaming.py
a4f/beta/_types.py
a4f/beta/pagination.py
a4f/beta/_extras/__init__.py
a4f/beta/_extras/_common.py
a4f/beta/_extras/numpy_proxy.py
a4f/beta/_extras/pandas_proxy.py
a4f/beta/_extras/sounddevice_proxy.py
a4f/beta/_utils/__init__.py
a4f/beta/_utils/_compat.py
a4f/beta/_utils/_datetime_parse.py
a4f/beta/_utils/_logs.py
a4f/beta/_utils/_proxy.py
a4f/beta/_utils/_reflection.py
a4f/beta/_utils/_resources_proxy.py
a4f/beta/_utils/_streams.py
a4f/beta/_utils/_sync.py
a4f/beta/_utils/_transform.py
a4f/beta/_utils/_typing.py
a4f/beta/_utils/_utils.py
a4f/beta/resources/__init__.py
a4f/beta/resources/embeddings.py
a4f/beta/resources/images.py
a4f/beta/resources/audio/__init__.py
a4f/beta/resources/audio/audio.py
a4f/beta/resources/audio/speech.py
a4f/beta/resources/audio/transcriptions.py
a4f/beta/resources/chat/__init__.py
a4f/beta/resources/chat/chat.py
a4f/beta/resources/chat/completions/__init__.py
a4f/beta/resources/chat/completions/completions.py
a4f/beta/resources/chat/completions/messages.py
a4f/beta/types/__init__.py
a4f/beta/types/audio_response_format.py
a4f/beta/types/auto_file_chunking_strategy_param.py
a4f/beta/types/completion.py
a4f/beta/types/completion_choice.py
a4f/beta/types/completion_create_params.py
a4f/beta/types/completion_usage.py
a4f/beta/types/create_embedding_response.py
a4f/beta/types/embedding.py
a4f/beta/types/embedding_create_params.py
a4f/beta/types/image.py
a4f/beta/types/image_create_variation_params.py
a4f/beta/types/image_edit_completed_event.py
a4f/beta/types/image_edit_params.py
a4f/beta/types/image_edit_partial_image_event.py
a4f/beta/types/image_edit_stream_event.py
a4f-1.0.5.dist-info/licenses/LICENSE
a4f-1.0.5.dist-info/METADATA
a4f-1.0.5.dist-info/WHEEL
a4f-1.0.5.dist-info/top_level.txt
a4f-1.0.5.dist-info/RECORD
