Metadata-Version: 2.4
Name: a4f
Version: 1.0.5
Summary: Official Python SDK for A4F - Unified AI Gateway for chat, images, audio, and embeddings
Author-email: Muhammad Gohar <mg03164525711@gmail.com>
License: MIT
Project-URL: Homepage, https://a4f.co/
Project-URL: Documentation, https://a4f.co/docs
Keywords: a4f,ai,machine learning,api client,ml,artificial intelligence,chat-gpt,image-generation,speech-recognition,embeddings,llm,cli,sdk,free
Classifier: Development Status :: 5 - Production/Stable
Classifier: Intended Audience :: Developers
Classifier: Intended Audience :: Science/Research
Classifier: License :: OSI Approved :: MIT License
Classifier: Operating System :: OS Independent
Classifier: Programming Language :: Python :: 3
Classifier: Programming Language :: Python :: 3.8
Classifier: Programming Language :: Python :: 3.9
Classifier: Programming Language :: Python :: 3.10
Classifier: Programming Language :: Python :: 3.11
Classifier: Programming Language :: Python :: 3.12
Classifier: Programming Language :: Python :: 3.13
Classifier: Topic :: Software Development :: Libraries :: Python Modules
Classifier: Topic :: Scientific/Engineering :: Artificial Intelligence
Classifier: Topic :: Scientific/Engineering :: Image Processing
Classifier: Topic :: Multimedia :: Sound/Audio :: Speech
Classifier: Typing :: Typed
Requires-Python: >=3.8
License-File: LICENSE
Requires-Dist: requests>=2.32.0
Requires-Dist: httpx>=0.27.0
Requires-Dist: aiohttp>=3.10.0
Requires-Dist: pydantic>=2.7.0
Requires-Dist: typing-extensions>=4.12.0
Requires-Dist: numpy>=1.26.0
Requires-Dist: pandas>=2.2.0
Requires-Dist: click>=8.1.7
Requires-Dist: rich>=13.9.0
Requires-Dist: tqdm>=4.66.4
Requires-Dist: sounddevice>=0.5.0
Dynamic: license-file
